Metadata-Version: 2.1
Name: qpd
Version: 0.3.2
Summary: Query Pandas Using SQL
Home-page: http://github.com/goodwanghan/qpd
Author: Han Wang
Author-email: goodwanghan@gmail.com
License: Apache-2.0
Keywords: pandas sql
Platform: UNKNOWN
Classifier: Development Status :: 3 - Alpha
Classifier: Intended Audience :: Developers
Classifier: Topic :: Software Development :: Libraries :: Python Modules
Classifier: License :: OSI Approved :: Apache Software License
Classifier: Programming Language :: Python :: 3.6
Classifier: Programming Language :: Python :: 3.7
Classifier: Programming Language :: Python :: 3.8
Classifier: Programming Language :: Python :: 3.9
Classifier: Programming Language :: Python :: 3.10
Classifier: Programming Language :: Python :: 3 :: Only
Requires-Python: >=3.6
Requires-Dist: pandas (>=1.0.2)
Requires-Dist: triad
Requires-Dist: adagio
Requires-Dist: sqlalchemy
Requires-Dist: antlr4-python3-runtime (>=4.10)
Provides-Extra: all
Requires-Dist: dask[dataframe] ; extra == 'all'
Requires-Dist: cloudpickle (>=1.4.0) ; extra == 'all'
Requires-Dist: modin[ray] ; extra == 'all'
Provides-Extra: dask
Requires-Dist: dask[dataframe] ; extra == 'dask'
Requires-Dist: cloudpickle (>=1.4.0) ; extra == 'dask'
Provides-Extra: ray
Requires-Dist: pandas (>=1.1.2) ; extra == 'ray'
Requires-Dist: modin[ray] (>=0.8.1.1) ; extra == 'ray'
